petra_grid-1.0.0.dist-info/METADATA
petra_grid-1.0.0.dist-info/WHEEL
petra_grid-1.0.0.dist-info/license_files/LICENSE
petra_grid/__init__.py
petra_grid/__init__.pyi
petra_grid/py.typed
petra_grid/petra_grid.cpython-38-aarch64-linux-gnu.so
petra_grid-1.0.0.dist-info/RECORD
