Metadata-Version: 2.1
Name: petra_grid
Version: 1.0.0
Classifier: Programming Language :: Rust
Classifier: Programming Language :: Python :: Implementation :: CPython
Classifier: Programming Language :: Python :: Implementation :: PyPy
Requires-Dist: numpy>=1.16.0
License-File: LICENSE
Summary: Python bindings for the petra_grid crate
Author: Derrick W. Turk <dwt@terminusdatascience.com>
Author-email: Derrick W. Turk <dwt@terminusdatascience.com>
License: MIT
Requires-Python: >=3.7
Project-URL: Source Code, https://github.com/derrickturk/petra_grid_py
